skippa/__init__.py
skippa/app.py
skippa/pipeline.py
skippa/profile.py
skippa/utils.py
skippa/transformers/__init__.py
skippa/transformers/base.py
skippa/transformers/custom.py
skippa/transformers/sklearn.py
skippa-0.1.16.dist-info/LICENSE
skippa-0.1.16.dist-info/METADATA
skippa-0.1.16.dist-info/WHEEL
skippa-0.1.16.dist-info/top_level.txt
skippa-0.1.16.dist-info/RECORD
