Metadata-Version: 2.1
Name: skippa
Version: 0.1.16
Summary: SciKIt-learn Pre-processing Pipeline in PAndas
Home-page: https://github.com/data-science-lab-amsterdam/skippa
Author: Robert van Straalen
Author-email: tech@datasciencelab.nl
License: UNKNOWN
Project-URL: Documentation, https://skippa.readthedocs.io/
Keywords: preprocessing pipeline pandas sklearn
Platform: UNKNOWN
Classifier: Development Status :: 2 - Pre-Alpha
Classifier: Intended Audience :: Developers
Classifier: Natural Language :: English
Classifier: Programming Language :: Python :: 3
Classifier: Programming Language :: Python :: 3.7
Classifier: Programming Language :: Python :: 3.8
Classifier: Programming Language :: Python :: 3.9
Classifier: Programming Language :: Python :: 3.10
Requires-Python: >=3.7
Requires-Dist: pandas
Requires-Dist: scikit-learn
Requires-Dist: dill
Provides-Extra: gradio
Requires-Dist: gradio ; extra == 'gradio'
